{"0": "Public Watchdog & Tallying UI", "1": "React App & Layout Components", "2": "Keyholder Auth & Passphrase Verification", "3": "Blockchain Package Config", "4": "Backend Package Config", "5": "Project Docs & Core Concepts", "6": "Merkle Contract Bindings", "7": "ElGamal Crypto (Backend)", "8": "Frontend TypeScript Config", "9": "Frontend Dependencies", "10": "Backend TypeScript Config", "11": "Frontend Node TS Config", "12": "Shared TypeScript Interfaces", "13": "Backend Runtime Dependencies", "14": "Frontend React Dependencies", "15": "Root Package & Orchestration", "16": "Blockchain TypeScript Config", "17": "Shamir Secret Sharing", "18": "ElGamal Crypto (Frontend)", "19": "Voter Seeding Scripts", "20": "Schema Migration Scripts", "21": "Frontend Lint Config", "22": "Candidate Seeding Scripts", "23": "Design System & UI Assets", "24": "Frontend TS Project References", "25": "Hardhat Config", "26": "Smart Contract Deploy Script", "27": "Frontend HTML & Favicon", "28": "Tailwind CSS Config", "29": "Graphify Knowledge Graph Rules", "30": "PostCSS Config", "31": "Frontend Vite README", "32": "Vite Build Config"}